{
  "IcoMoonType": "selection",
  "icons": [
    {
      "icon": {
        "paths": [
          "M512 1024c282.77 0 512-229.23 512-512s-229.23-512-512-512-512 229.23-512 512 229.23 512 512 512zM512 96c229.75 0 416 186.25 416 416s-186.25 416-416 416-416-186.25-416-416 186.25-416 416-416zM512 598.76c115.95 0 226.23-30.806 320-84.92-14.574 178.438-153.128 318.16-320 318.16-166.868 0-305.422-139.872-320-318.304 93.77 54.112 204.050 85.064 320 85.064zM256 352c0-53.019 28.654-96 64-96s64 42.981 64 96c0 53.019-28.654 96-64 96s-64-42.981-64-96zM640 352c0-53.019 28.654-96 64-96s64 42.981 64 96c0 53.019-28.654 96-64 96s-64-42.981-64-96z"
        ],
        "tags": [
          "happy",
          "emoticon",
          "smiley",
          "face"
        ],
        "defaultCode": 59871,
        "grid": 16,
        "attrs": []
      },
      "attrs": [],
      "properties": {
        "ligatures": "happy, emoticon",
        "name": "happy",
        "order": 61,
        "id": 224,
        "prevSize": 32,
        "code": 59871
      },
      "setIdx": 0,
      "setId": 1,
      "iconIdx": 223
    },
    {
      "icon": {
        "paths": [
          "M512 0c-282.77 0-512 229.23-512 512s229.23 512 512 512 512-229.23 512-512-229.23-512-512-512zM704 256c35.348 0 64 42.98 64 96s-28.652 96-64 96-64-42.98-64-96 28.652-96 64-96zM320 256c35.346 0 64 42.98 64 96s-28.654 96-64 96-64-42.98-64-96 28.654-96 64-96zM512 896c-166.868 0-305.422-139.872-320-318.304 93.77 54.114 204.050 85.064 320 85.064s226.23-30.806 320-84.92c-14.574 178.438-153.128 318.16-320 318.16z"
        ],
        "tags": [
          "happy",
          "emoticon",
          "smiley",
          "face"
        ],
        "defaultCode": 59872,
        "grid": 16,
        "attrs": []
      },
      "attrs": [],
      "properties": {
        "ligatures": "happy2, emoticon2",
        "name": "happy2",
        "order": 59,
        "id": 225,
        "prevSize": 32,
        "code": 59872
      },
      "setIdx": 0,
      "setId": 1,
      "iconIdx": 224
    },
    {
      "icon": {
        "paths": [
          "M512 1024c282.77 0 512-229.23 512-512s-229.23-512-512-512-512 229.23-512 512 229.23 512 512 512zM512 96c229.75 0 416 186.25 416 416s-186.25 416-416 416-416-186.25-416-416 186.25-416 416-416zM256 320c0-35.346 28.654-64 64-64s64 28.654 64 64c0 35.346-28.654 64-64 64s-64-28.654-64-64zM640 320c0-35.346 28.654-64 64-64s64 28.654 64 64c0 35.346-28.654 64-64 64s-64-28.654-64-64zM704.098 627.26l82.328 49.396c-55.962 93.070-157.916 155.344-274.426 155.344s-218.464-62.274-274.426-155.344l82.328-49.396c39.174 65.148 110.542 108.74 192.098 108.74s152.924-43.592 192.098-108.74z"
        ],
        "tags": [
          "smile",
          "emoticon",
          "smiley",
          "face"
        ],
        "defaultCode": 59873,
        "grid": 16,
        "attrs": []
      },
      "attrs": [],
      "properties": {
        "ligatures": "smile, emoticon3",
        "name": "smile",
        "order": 57,
        "id": 226,
        "prevSize": 32,
        "code": 59873
      },
      "setIdx": 0,
      "setId": 1,
      "iconIdx": 225
    },
    {
      "icon": {
        "paths": [
          "M512 0c-282.77 0-512 229.23-512 512s229.23 512 512 512 512-229.23 512-512-229.23-512-512-512zM704 256c35.346 0 64 28.654 64 64s-28.654 64-64 64-64-28.654-64-64 28.654-64 64-64zM320 256c35.346 0 64 28.654 64 64s-28.654 64-64 64-64-28.654-64-64 28.654-64 64-64zM512 832c-116.51 0-218.464-62.274-274.426-155.344l82.328-49.396c39.174 65.148 110.542 108.74 192.098 108.74s152.924-43.592 192.098-108.74l82.328 49.396c-55.962 93.070-157.916 155.344-274.426 155.344z"
        ],
        "tags": [
          "smile",
          "emoticon",
          "smiley",
          "face"
        ],
        "defaultCode": 59874,
        "grid": 16,
        "attrs": []
      },
      "attrs": [],
      "properties": {
        "ligatures": "smile2, emoticon4",
        "name": "smile2",
        "order": 55,
        "id": 227,
        "prevSize": 32,
        "code": 59874
      },
      "setIdx": 0,
      "setId": 1,
      "iconIdx": 226
    },
    {
      "icon": {
        "paths": [
          "M512 1024c282.77 0 512-229.23 512-512s-229.23-512-512-512-512 229.23-512 512 229.23 512 512 512zM512 96c229.75 0 416 186.25 416 416s-186.25 416-416 416-416-186.25-416-416 186.25-416 416-416zM256 320c0-35.346 28.654-64 64-64s64 28.654 64 64c0 35.346-28.654 64-64 64s-64-28.654-64-64zM640 320c0-35.346 28.654-64 64-64s64 28.654 64 64c0 35.346-28.654 64-64 64s-64-28.654-64-64zM768 576v64h-64v96c0 53.020-42.98 96-96 96s-96-42.98-96-96v-96h-256v-64h512z"
        ],
        "tags": [
          "tongue",
          "emoticon",
          "smiley",
          "face"
        ],
        "defaultCode": 59875,
        "grid": 16,
        "attrs": []
      },
      "attrs": [],
      "properties": {
        "ligatures": "tongue, emoticon5",
        "name": "tongue",
        "order": 53,
        "id": 228,
        "prevSize": 32,
        "code": 59875
      },
      "setIdx": 0,
      "setId": 1,
      "iconIdx": 227
    },
    {
      "icon": {
        "paths": [
          "M512 0c-282.77 0-512 229.23-512 512s229.23 512 512 512 512-229.23 512-512-229.23-512-512-512zM320 256c35.346 0 64 28.654 64 64s-28.654 64-64 64-64-28.654-64-64 28.654-64 64-64zM768 640h-64v96c0 53.020-42.98 96-96 96s-96-42.98-96-96v-96h-256v-64h512v64zM704 384c-35.346 0-64-28.654-64-64s28.654-64 64-64 64 28.654 64 64-28.654 64-64 64z"
        ],
        "tags": [
          "tongue",
          "emoticon",
          "smiley",
          "face"
        ],
        "defaultCode": 59876,
        "grid": 16,
        "attrs": []
      },
      "attrs": [],
      "properties": {
        "ligatures": "tongue2, emoticon6",
        "name": "tongue2",
        "order": 45,
        "id": 229,
        "prevSize": 32,
        "code": 59876
      },
      "setIdx": 0,
      "setId": 1,
      "iconIdx": 228
    },
    {
      "icon": {
        "paths": [
          "M512 1024c282.77 0 512-229.23 512-512s-229.23-512-512-512-512 229.23-512 512 229.23 512 512 512zM512 96c229.75 0 416 186.25 416 416s-186.25 416-416 416-416-186.25-416-416 186.25-416 416-416zM256 320c0-35.346 28.654-64 64-64s64 28.654 64 64c0 35.346-28.654 64-64 64s-64-28.654-64-64zM640 320c0-35.346 28.654-64 64-64s64 28.654 64 64c0 35.346-28.654 64-64 64s-64-28.654-64-64zM319.902 780.74l-82.328-49.396c55.962-93.070 157.916-155.344 274.426-155.344 116.508 0 218.462 62.274 274.426 155.344l-82.328 49.396c-39.174-65.148-110.542-108.74-192.098-108.74-81.558 0-152.924 43.592-192.098 108.74z"
        ],
        "tags": [
          "sad",
          "emoticon",
          "smiley",
          "face"
        ],
        "defaultCode": 59877,
        "grid": 16,
        "attrs": []
      },
      "attrs": [],
      "properties": {
        "ligatures": "sad, emoticon7",
        "name": "sad",
        "order": 44,
        "id": 230,
        "prevSize": 32,
        "code": 59877
      },
      "setIdx": 0,
      "setId": 1,
      "iconIdx": 229
    },
    {
      "icon": {
        "paths": [
          "M512 0c-282.77 0-512 229.23-512 512s229.23 512 512 512 512-229.23 512-512-229.23-512-512-512zM704 256c35.346 0 64 28.654 64 64s-28.654 64-64 64-64-28.654-64-64 28.654-64 64-64zM320 256c35.346 0 64 28.654 64 64s-28.654 64-64 64-64-28.654-64-64 28.654-64 64-64zM704.098 780.74c-39.174-65.148-110.544-108.74-192.098-108.74-81.556 0-152.924 43.592-192.098 108.74l-82.328-49.396c55.96-93.070 157.916-155.344 274.426-155.344 116.508 0 218.464 62.274 274.426 155.344l-82.328 49.396z"
        ],
        "tags": [
          "sad",
          "emoticon",
          "smiley",
          "face"
        ],
        "defaultCode": 59878,
        "grid": 16,
        "attrs": []
      },
      "attrs": [],
      "properties": {
        "ligatures": "sad2, emoticon8",
        "name": "sad2",
        "order": 43,
        "id": 231,
        "prevSize": 32,
        "code": 59878
      },
      "setIdx": 0,
      "setId": 1,
      "iconIdx": 230
    },
    {
      "icon": {
        "paths": [
          "M512 1024c282.77 0 512-229.23 512-512s-229.23-512-512-512-512 229.23-512 512 229.23 512 512 512zM512 96c229.75 0 416 186.25 416 416s-186.25 416-416 416-416-186.25-416-416 186.25-416 416-416zM542.74 711.028c140.248-27.706 249.11-91.542 288.454-176.594-21.654 167.956-161.518 297.566-330.85 297.566-119.242 0-223.858-64.282-282.892-160.948 70.41 55.058 194.534 65.808 325.288 39.976zM640 352c0-53.019 28.654-96 64-96s64 42.981 64 96c0 53.019-28.654 96-64 96s-64-42.981-64-96zM352 371.5c-41.796 0-77.334 15.656-90.516 37.5-3.54-5.866-5.484-32.174-5.484-38.75 0-31.066 42.98-56.25 96-56.25s96 25.184 96 56.25c0 6.576-1.944 32.884-5.484 38.75-13.182-21.844-48.72-37.5-90.516-37.5z"
        ],
        "tags": [
          "wink",
          "emoticon",
          "smiley",
          "face"
        ],
        "defaultCode": 59879,
        "grid": 16,
        "attrs": []
      },
      "attrs": [],
      "properties": {
        "ligatures": "wink, emoticon9",
        "name": "wink",
        "order": 42,
        "id": 232,
        "prevSize": 32,
        "code": 59879
      },
      "setIdx": 0,
      "setId": 1,
      "iconIdx": 231
    },
    {
      "icon": {
        "paths": [
          "M512 0c-282.77 0-512 229.228-512 512 0 282.77 229.228 512 512 512 282.77 0 512-229.23 512-512 0-282.772-229.23-512-512-512zM704 256c35.346 0 64 42.98 64 96s-28.654 96-64 96-64-42.98-64-96 28.654-96 64-96zM352 312.062c59.646 0 102 22.332 102 57.282 0 7.398 3.812 42.994-0.17 49.594-14.828-24.576-54.81-42.188-101.83-42.188s-87.002 17.612-101.83 42.188c-3.982-6.6-0.17-42.196-0.17-49.594 0-34.95 42.354-57.282 102-57.282zM500.344 832c-119.242 0-223.858-64.28-282.892-160.952 70.41 55.060 194.534 65.81 325.288 39.978 140.248-27.706 249.11-91.542 288.454-176.594-21.654 167.96-161.518 297.568-330.85 297.568z"
        ],
        "tags": [
          "wink",
          "emoticon",
          "smiley",
          "face"
        ],
        "defaultCode": 59880,
        "grid": 16,
        "attrs": []
      },
      "attrs": [],
      "properties": {
        "ligatures": "wink2, emoticon10",
        "name": "wink2",
        "order": 41,
        "id": 233,
        "prevSize": 32,
        "code": 59880
      },
      "setIdx": 0,
      "setId": 1,
      "iconIdx": 232
    },
    {
      "icon": {
        "paths": [
          "M512 1024c282.77 0 512-229.23 512-512s-229.23-512-512-512-512 229.23-512 512 229.23 512 512 512zM512 96c229.75 0 416 186.25 416 416s-186.25 416-416 416-416-186.25-416-416 186.25-416 416-416zM192 512v64c0 140.8 115.2 256 256 256h128c140.8 0 256-115.2 256-256v-64h-640zM384 756.988c-26.538-9.458-50.924-24.822-71.544-45.446-36.406-36.402-56.456-84.54-56.456-135.542h128v180.988zM576 768h-128v-192h128v192zM711.544 711.542c-20.624 20.624-45.010 35.988-71.544 45.446v-180.988h128c0 51.002-20.048 99.14-56.456 135.542zM225.352 384c0.002 0 0 0 0 0 9.768 0 18.108-7.056 19.724-16.69 6.158-36.684 37.668-63.31 74.924-63.31s68.766 26.626 74.924 63.31c1.616 9.632 9.956 16.69 19.722 16.69 9.768 0 18.108-7.056 19.724-16.688 1.082-6.436 1.628-12.934 1.628-19.312 0-63.962-52.038-116-116-116s-116 52.038-116 116c0 6.378 0.548 12.876 1.628 19.312 1.62 9.632 9.96 16.688 19.726 16.688zM609.352 384c0.002 0 0 0 0 0 9.77 0 18.112-7.056 19.724-16.69 6.158-36.684 37.668-63.31 74.924-63.31s68.766 26.626 74.924 63.31c1.616 9.632 9.958 16.69 19.722 16.69s18.108-7.056 19.722-16.688c1.082-6.436 1.628-12.934 1.628-19.312 0-63.962-52.038-116-116-116s-116 52.038-116 116c0 6.378 0.544 12.876 1.626 19.312 1.624 9.632 9.964 16.688 19.73 16.688z"
        ],
        "tags": [
          "grin",
          "emoticon",
          "smiley",
          "face"
        ],
        "defaultCode": 59881,
        "grid": 16,
        "attrs": []
      },
      "attrs": [],
      "properties": {
        "ligatures": "grin, emoticon11",
        "name": "grin",
        "order": 40,
        "id": 234,
        "prevSize": 32,
        "code": 59881
      },
      "setIdx": 0,
      "setId": 1,
      "iconIdx": 233
    },
    {
      "icon": {
        "paths": [
          "M512 0c-282.77 0-512 229.23-512 512s229.226 512 512 512c282.77 0 512-229.23 512-512s-229.23-512-512-512zM704 236c63.962 0 116 52.038 116 116 0 6.378-0.546 12.876-1.628 19.312-1.618 9.632-9.958 16.688-19.724 16.688s-18.108-7.056-19.722-16.69c-6.16-36.684-37.67-53.31-74.926-53.31s-68.766 16.626-74.924 53.31c-1.616 9.632-9.956 16.69-19.722 16.69-0.002 0 0 0-0.002 0-9.766 0-18.106-7.056-19.722-16.688-1.084-6.436-1.63-12.934-1.63-19.312 0-63.962 52.038-116 116-116zM320 236c63.962 0 116 52.038 116 116 0 6.378-0.548 12.876-1.628 19.312-1.618 9.632-9.956 16.688-19.724 16.688s-18.106-7.056-19.722-16.69c-6.16-36.684-37.67-53.31-74.926-53.31s-68.766 16.626-74.924 53.31c-1.616 9.632-9.956 16.69-19.722 16.69 0 0 0 0 0 0-9.766 0-18.106-7.056-19.724-16.688-1.082-6.436-1.63-12.934-1.63-19.312 0-63.962 52.038-116 116-116zM192 576h192v247.846c-110.094-28.606-192-129.124-192-247.846zM448 832v-256h128v256h-128zM640 823.846v-247.846h192c0 118.722-81.904 219.24-192 247.846z"
        ],
        "tags": [
          "grin",
          "emoticon",
          "smiley",
          "face"
        ],
        "defaultCode": 59882,
        "grid": 16,
        "attrs": []
      },
      "attrs": [],
      "properties": {
        "ligatures": "grin2, emoticon12",
        "name": "grin2",
        "order": 73,
        "id": 235,
        "prevSize": 32,
        "code": 59882
      },
      "setIdx": 0,
      "setId": 1,
      "iconIdx": 234
    },
    {
      "icon": {
        "paths": [
          "M512 1024c282.77 0 512-229.23 512-512s-229.23-512-512-512-512 229.23-512 512 229.23 512 512 512zM512 96c229.75 0 416 186.25 416 416s-186.25 416-416 416-416-186.25-416-416 186.25-416 416-416zM800 256c17.6 0 32 14.4 32 32v96c0 35.2-28.8 64-64 64h-128c-35.2 0-64-28.8-64-64h-128c0 35.2-28.8 64-64 64h-128c-35.2 0-64-28.8-64-64v-96c0-17.6 14.4-32 32-32h192c17.6 0 32 14.4 32 32v32h128v-32c0-17.6 14.4-32 32-32h192zM512 768c93.208 0 174.772-49.818 219.546-124.278l54.88 32.934c-55.966 93.070-157.916 155.344-274.426 155.344-48.458 0-94.384-10.796-135.54-30.082l33.162-55.278c31.354 13.714 65.964 21.36 102.378 21.36z"
        ],
        "tags": [
          "cool",
          "emoticon",
          "smiley",
          "face"
        ],
        "defaultCode": 59883,
        "grid": 16,
        "attrs": []
      },
      "attrs": [],
      "properties": {
        "ligatures": "cool, emoticon13",
        "name": "cool",
        "order": 72,
        "id": 236,
        "prevSize": 32,
        "code": 59883
      },
      "setIdx": 0,
      "setId": 1,
      "iconIdx": 235
    },
    {
      "icon": {
        "paths": [
          "M512 0c-282.77 0-512 229.23-512 512s229.226 512 512 512c282.77 0 512-229.23 512-512s-229.23-512-512-512zM512 832c-48.458 0-94.384-10.796-135.542-30.082l33.162-55.276c31.356 13.712 65.966 21.358 102.38 21.358 93.208 0 174.772-49.818 219.542-124.278l54.882 32.934c-55.964 93.070-157.914 155.344-274.424 155.344zM832 384c0 35.2-28.8 64-64 64h-128c-35.2 0-64-28.8-64-64h-128c0 35.2-28.8 64-64 64h-128c-35.2 0-64-28.8-64-64v-96c0-17.6 14.4-32 32-32h192c17.6 0 32 14.4 32 32v32h128v-32c0-17.6 14.4-32 32-32h192c17.6 0 32 14.4 32 32v96z"
        ],
        "tags": [
          "cool",
          "emoticon",
          "smiley",
          "face"
        ],
        "defaultCode": 59884,
        "grid": 16,
        "attrs": []
      },
      "attrs": [],
      "properties": {
        "ligatures": "cool2, emoticon14",
        "name": "cool2",
        "order": 71,
        "id": 237,
        "prevSize": 32,
        "code": 59884
      },
      "setIdx": 0,
      "setId": 1,
      "iconIdx": 236
    },
    {
      "icon": {
        "paths": [
          "M512 1024c282.77 0 512-229.23 512-512s-229.23-512-512-512-512 229.23-512 512 229.23 512 512 512zM512 96c229.75 0 416 186.25 416 416s-186.25 416-416 416-416-186.25-416-416 186.25-416 416-416zM704.098 780.74c-39.174-65.148-110.544-108.74-192.098-108.74-81.556 0-152.924 43.592-192.098 108.74l-82.328-49.396c55.96-93.070 157.916-155.344 274.426-155.344 116.508 0 218.464 62.274 274.426 155.344l-82.328 49.396zM767.042 280.24c4.284 17.144-6.14 34.518-23.282 38.804-17.626 4.45-38.522 12.12-56.936 21.35 10.648 11.43 17.174 26.752 17.174 43.606 0 35.346-28.654 64-64 64s-64-28.654-64-64c0-1.17 0.036-2.33 0.098-3.484 2.032-47.454 45.212-78.946 81.592-97.138 34.742-17.37 69.102-26.060 70.548-26.422 17.146-4.288 34.518 6.138 38.806 23.284zM256.958 280.24c4.288-17.146 21.66-27.572 38.806-23.284 1.446 0.362 35.806 9.052 70.548 26.422 36.38 18.192 79.56 49.684 81.592 97.138 0.062 1.154 0.098 2.314 0.098 3.484 0 35.346-28.654 64-64 64s-64-28.654-64-64c0-16.854 6.526-32.176 17.174-43.606-18.414-9.23-39.31-16.9-56.936-21.35-17.142-4.286-27.566-21.66-23.282-38.804z"
        ],
        "tags": [
          "angry",
          "emoticon",
          "smiley",
          "face",
          "rage"
        ],
        "defaultCode": 59885,
        "grid": 16,
        "attrs": []
      },
      "attrs": [],
      "properties": {
        "ligatures": "angry, emoticon15",
        "name": "angry",
        "order": 66,
        "id": 238,
        "prevSize": 32,
        "code": 59885
      },
      "setIdx": 0,
      "setId": 1,
      "iconIdx": 237
    },
    {
      "icon": {
        "paths": [
          "M512 0c-282.77 0-512 229.23-512 512s229.23 512 512 512 512-229.23 512-512-229.23-512-512-512zM576.094 380.516c2.032-47.454 45.21-78.948 81.592-97.138 34.742-17.372 69.104-26.060 70.548-26.422 17.146-4.288 34.52 6.138 38.806 23.284s-6.138 34.518-23.284 38.806c-17.624 4.45-38.522 12.12-56.936 21.35 10.648 11.43 17.174 26.752 17.174 43.606 0 35.346-28.654 64-64 64s-64-28.654-64-64c0.002-1.17 0.038-2.332 0.1-3.486zM256.958 280.24c4.288-17.146 21.66-27.572 38.806-23.284 1.446 0.362 35.806 9.052 70.548 26.422 36.38 18.192 79.56 49.684 81.592 97.138 0.062 1.154 0.098 2.314 0.098 3.484 0 35.346-28.654 64-64 64s-64-28.654-64-64c0-16.854 6.526-32.176 17.174-43.606-18.414-9.23-39.31-16.9-56.936-21.35-17.142-4.286-27.566-21.66-23.282-38.804zM704.098 780.74c-39.174-65.148-110.544-108.74-192.098-108.74-81.556 0-152.924 43.592-192.098 108.74l-82.328-49.396c55.96-93.070 157.916-155.344 274.426-155.344 116.508 0 218.464 62.274 274.426 155.344l-82.328 49.396z"
        ],
        "tags": [
          "angry",
          "emoticon",
          "smiley",
          "face",
          "rage"
        ],
        "defaultCode": 59886,
        "grid": 16,
        "attrs": []
      },
      "attrs": [],
      "properties": {
        "ligatures": "angry2, emoticon16",
        "name": "angry2",
        "order": 65,
        "id": 239,
        "prevSize": 32,
        "code": 59886
      },
      "setIdx": 0,
      "setId": 1,
      "iconIdx": 238
    },
    {
      "icon": {
        "paths": [
          "M639.996 448c-35.346 0-64-28.654-63.998-64.002 0-1.17 0.036-2.33 0.098-3.484 2.032-47.454 45.212-78.946 81.592-97.138 34.742-17.37 69.102-26.060 70.548-26.422 17.146-4.288 34.518 6.138 38.806 23.284 4.284 17.146-6.14 34.518-23.284 38.806-17.626 4.45-38.522 12.12-56.936 21.35 10.648 11.43 17.174 26.752 17.174 43.606 0 35.346-28.654 64-64 64zM280.242 319.044c-17.144-4.286-27.568-21.66-23.282-38.804 4.286-17.146 21.66-27.572 38.806-23.284 1.444 0.362 35.806 9.050 70.548 26.422 36.382 18.19 79.56 49.684 81.592 97.138 0.062 1.154 0.098 2.316 0.098 3.484 0 35.346-28.654 64-64 64s-64-28.654-64-64c0-16.854 6.526-32.176 17.174-43.606-18.414-9.23-39.312-16.9-56.936-21.35zM512 736c81.554 0 152.924-43.592 192.098-108.74l82.328 49.396c-55.962 93.070-157.916 155.344-274.426 155.344s-218.464-62.274-274.426-155.344l82.328-49.396c39.174 65.148 110.542 108.74 192.098 108.74zM1024 64c0-45.516-9.524-88.8-26.652-128-33.576 76.836-96.448 137.932-174.494 169.178-86.194-65.96-193.936-105.178-310.854-105.178s-224.66 39.218-310.854 105.178c-78.048-31.246-140.918-92.342-174.494-169.178-17.128 39.2-26.652 82.484-26.652 128 0 73.574 24.85 141.328 66.588 195.378-42.37 74.542-66.588 160.75-66.588 252.622 0 282.77 229.23 512 512 512s512-229.23 512-512c0-91.872-24.218-178.080-66.588-252.622 41.738-54.050 66.588-121.804 66.588-195.378zM512 928c-229.75 0-416-186.25-416-416s186.25-416 416-416 416 186.25 416 416-186.25 416-416 416z"
        ],
        "tags": [
          "evil",
          "emoticon",
          "smiley",
          "face"
        ],
        "defaultCode": 59887,
        "grid": 16,
        "attrs": []
      },
      "attrs": [],
      "properties": {
        "ligatures": "evil, emoticon17",
        "name": "evil",
        "order": 64,
        "id": 240,
        "prevSize": 32,
        "code": 59887
      },
      "setIdx": 0,
      "setId": 1,
      "iconIdx": 239
    },
    {
      "icon": {
        "paths": [
          "M1024 64c0-45.516-9.524-88.8-26.652-128-33.576 76.836-96.448 137.932-174.494 169.178-86.194-65.96-193.936-105.178-310.854-105.178s-224.66 39.218-310.854 105.178c-78.048-31.246-140.918-92.342-174.494-169.178-17.128 39.2-26.652 82.484-26.652 128 0 73.574 24.85 141.328 66.588 195.378-42.37 74.542-66.588 160.75-66.588 252.622 0 282.77 229.23 512 512 512s512-229.23 512-512c0-91.872-24.218-178.080-66.588-252.622 41.738-54.050 66.588-121.804 66.588-195.378zM576.094 380.516c2.032-47.454 45.21-78.948 81.592-97.138 34.742-17.372 69.104-26.060 70.548-26.422 17.146-4.288 34.52 6.138 38.806 23.284s-6.138 34.518-23.284 38.806c-17.624 4.45-38.522 12.12-56.936 21.35 10.648 11.43 17.174 26.752 17.174 43.606 0 35.346-28.654 64-64 64s-64-28.654-64-64c0.002-1.17 0.038-2.332 0.1-3.486zM256.958 280.24c4.288-17.146 21.66-27.572 38.806-23.284 1.446 0.362 35.806 9.052 70.548 26.422 36.38 18.192 79.56 49.684 81.592 97.138 0.062 1.154 0.098 2.314 0.098 3.484 0 35.346-28.654 64-64 64s-64-28.654-64-64c0-16.854 6.526-32.176 17.174-43.606-18.414-9.23-39.31-16.9-56.936-21.35-17.142-4.286-27.566-21.66-23.282-38.804zM512 832c-116.51 0-218.464-62.274-274.426-155.344l82.328-49.396c39.174 65.148 110.542 108.74 192.098 108.74 81.554 0 152.924-43.592 192.098-108.74l82.328 49.396c-55.962 93.070-157.916 155.344-274.426 155.344z"
        ],
        "tags": [
          "evil",
          "emoticon",
          "smiley",
          "face"
        ],
        "defaultCode": 59888,
        "grid": 16,
        "attrs": []
      },
      "attrs": [],
      "properties": {
        "ligatures": "evil2, emoticon18",
        "name": "evil2",
        "order": 63,
        "id": 241,
        "prevSize": 32,
        "code": 59888
      },
      "setIdx": 0,
      "setId": 1,
      "iconIdx": 240
    },
    {
      "icon": {
        "paths": [
          "M512 1024c282.77 0 512-229.23 512-512s-229.23-512-512-512-512 229.23-512 512 229.23 512 512 512zM512 96c229.75 0 416 186.25 416 416s-186.25 416-416 416-416-186.25-416-416 186.25-416 416-416zM384 704c0-70.692 57.308-128 128-128s128 57.308 128 128c0 70.692-57.308 128-128 128s-128-57.308-128-128zM640 352c0-53.019 28.654-96 64-96s64 42.981 64 96c0 53.019-28.654 96-64 96s-64-42.981-64-96zM256 352c0-53.019 28.654-96 64-96s64 42.981 64 96c0 53.019-28.654 96-64 96s-64-42.981-64-96z"
        ],
        "tags": [
          "shocked",
          "emoticon",
          "smiley",
          "face"
        ],
        "defaultCode": 59889,
        "grid": 16,
        "attrs": []
      },
      "attrs": [],
      "properties": {
        "ligatures": "shocked, emoticon19",
        "name": "shocked",
        "order": 62,
        "id": 242,
        "prevSize": 32,
        "code": 59889
      },
      "setIdx": 0,
      "setId": 1,
      "iconIdx": 241
    },
    {
      "icon": {
        "paths": [
          "M512 0c-282.77 0-512 229.23-512 512s229.23 512 512 512 512-229.23 512-512-229.23-512-512-512zM320 448c-35.346 0-64-42.98-64-96s28.654-96 64-96 64 42.98 64 96-28.654 96-64 96zM512 832c-70.692 0-128-57.308-128-128s57.308-128 128-128c70.692 0 128 57.308 128 128s-57.308 128-128 128zM704 448c-35.346 0-64-42.98-64-96s28.654-96 64-96 64 42.98 64 96-28.654 96-64 96z"
        ],
        "tags": [
          "shocked",
          "emoticon",
          "smiley",
          "face"
        ],
        "defaultCode": 59890,
        "grid": 16,
        "attrs": []
      },
      "attrs": [],
      "properties": {
        "ligatures": "shocked2, emoticon20",
        "name": "shocked2",
        "order": 60,
        "id": 243,
        "prevSize": 32,
        "code": 59890
      },
      "setIdx": 0,
      "setId": 1,
      "iconIdx": 242
    },
    {
      "icon": {
        "paths": [
          "M512 1024c282.77 0 512-229.23 512-512s-229.23-512-512-512-512 229.23-512 512 229.23 512 512 512zM512 96c229.75 0 416 186.25 416 416s-186.25 416-416 416-416-186.25-416-416 186.25-416 416-416z",
          "M384 416c0 17.673-14.327 32-32 32s-32-14.327-32-32c0-17.673 14.327-32 32-32s32 14.327 32 32z",
          "M352 320c53.020 0 96 42.98 96 96s-42.98 96-96 96-96-42.98-96-96 42.98-96 96-96zM352 256c-88.224 0-160 71.776-160 160s71.776 160 160 160 160-71.776 160-160-71.776-160-160-160v0z",
          "M704 416c0 17.673-14.327 32-32 32s-32-14.327-32-32c0-17.673 14.327-32 32-32s32 14.327 32 32z",
          "M672 320c53.020 0 96 42.98 96 96s-42.98 96-96 96-96-42.98-96-96 42.98-96 96-96zM672 256c-88.224 0-160 71.776-160 160s71.776 160 160 160 160-71.776 160-160-71.776-160-160-160v0z",
          "M384 704h256v64h-256v-64z"
        ],
        "tags": [
          "baffled",
          "emoticon",
          "smiley",
          "shocked",
          "face"
        ],
        "defaultCode": 59891,
        "grid": 16,
        "attrs": []
      },
      "attrs": [],
      "properties": {
        "ligatures": "baffled, emoticon21",
        "name": "baffled",
        "order": 58,
        "id": 244,
        "prevSize": 32,
        "code": 59891
      },
      "setIdx": 0,
      "setId": 1,
      "iconIdx": 243
    },
    {
      "icon": {
        "paths": [
          "M384 416c0 17.674-14.326 32-32 32s-32-14.326-32-32 14.326-32 32-32 32 14.326 32 32z",
          "M704 416c0 17.674-14.326 32-32 32s-32-14.326-32-32 14.326-32 32-32 32 14.326 32 32z",
          "M512 0c-282.77 0-512 229.23-512 512s229.23 512 512 512 512-229.23 512-512-229.23-512-512-512zM256 416c0-53.020 42.98-96 96-96s96 42.98 96 96-42.98 96-96 96-96-42.98-96-96zM640 768h-256v-64h256v64zM672 512c-53.020 0-96-42.98-96-96s42.98-96 96-96 96 42.98 96 96-42.98 96-96 96z"
        ],
        "tags": [
          "baffled",
          "emoticon",
          "smiley",
          "shocked",
          "face"
        ],
        "defaultCode": 59892,
        "grid": 16,
        "attrs": []
      },
      "attrs": [],
      "properties": {
        "ligatures": "baffled2, emoticon22",
        "name": "baffled2",
        "order": 56,
        "id": 245,
        "prevSize": 32,
        "code": 59892
      },
      "setIdx": 0,
      "setId": 1,
      "iconIdx": 244
    },
    {
      "icon": {
        "paths": [
          "M512 1024c282.77 0 512-229.23 512-512s-229.23-512-512-512-512 229.23-512 512 229.23 512 512 512zM512 96c229.75 0 416 186.25 416 416s-186.25 416-416 416-416-186.25-416-416 186.25-416 416-416zM256 320c0-35.346 28.654-64 64-64s64 28.654 64 64c0 35.346-28.654 64-64 64s-64-28.654-64-64zM640 320c0-35.346 28.654-64 64-64s64 28.654 64 64c0 35.346-28.654 64-64 64s-64-28.654-64-64zM726.106 640h64.864c9.246 72.506-32.452 144.53-103.958 170.56-82.904 30.176-174.9-12.716-205.080-95.616-18.108-49.744-73.306-75.482-123.048-57.372-45.562 16.588-70.956 64.298-60.988 110.424h-64.86c-9.242-72.508 32.45-144.528 103.956-170.56 82.904-30.178 174.902 12.716 205.082 95.614 18.104 49.748 73.306 75.482 123.044 57.372 45.562-16.584 70.956-64.298 60.988-110.422z"
        ],
        "tags": [
          "confused",
          "emoticon",
          "smiley",
          "face",
          "bewildered"
        ],
        "defaultCode": 59893,
        "grid": 16,
        "attrs": []
      },
      "attrs": [],
      "properties": {
        "ligatures": "confused, emoticon23",
        "name": "confused",
        "order": 54,
        "id": 246,
        "prevSize": 32,
        "code": 59893
      },
      "setIdx": 0,
      "setId": 1,
      "iconIdx": 245
    },
    {
      "icon": {
        "paths": [
          "M512 0c-282.77 0-512 229.23-512 512s229.226 512 512 512c282.77 0 512-229.23 512-512s-229.23-512-512-512zM704 256c35.346 0 64 28.654 64 64s-28.654 64-64 64-64-28.654-64-64c0-35.346 28.654-64 64-64zM320 256c35.346 0 64 28.654 64 64s-28.654 64-64 64-64-28.654-64-64c0-35.346 28.654-64 64-64zM687.010 810.56c-82.902 30.18-174.9-12.712-205.080-95.614-18.108-49.742-73.306-75.478-123.048-57.372-45.562 16.588-70.958 64.296-60.988 110.424h-64.86c-9.244-72.508 32.45-144.532 103.956-170.56 82.904-30.18 174.902 12.712 205.082 95.614 18.108 49.742 73.306 75.476 123.046 57.37 45.562-16.584 70.958-64.294 60.988-110.422h64.864c9.24 72.506-32.454 144.532-103.96 170.56z"
        ],
        "tags": [
          "confused",
          "emoticon",
          "smiley",
          "face",
          "bewildered"
        ],
        "defaultCode": 59894,
        "grid": 16,
        "attrs": []
      },
      "attrs": [],
      "properties": {
        "ligatures": "confused2, emoticon24",
        "name": "confused2",
        "order": 46,
        "id": 247,
        "prevSize": 32,
        "code": 59894
      },
      "setIdx": 0,
      "setId": 1,
      "iconIdx": 246
    },
    {
      "icon": {
        "paths": [
          "M512 1024c282.77 0 512-229.23 512-512s-229.23-512-512-512-512 229.23-512 512 229.23 512 512 512zM512 96c229.75 0 416 186.25 416 416s-186.25 416-416 416-416-186.25-416-416 186.25-416 416-416zM256 320c0 35.346 28.654 64 64 64s64-28.654 64-64-28.654-64-64-64-64 28.654-64 64zM640 320c0 35.346 28.654 64 64 64s64-28.654 64-64-28.654-64-64-64-64 28.654-64 64zM384 704h256v64h-256v-64z"
        ],
        "tags": [
          "neutral",
          "emoticon",
          "smiley",
          "face"
        ],
        "defaultCode": 59895,
        "grid": 16,
        "attrs": []
      },
      "attrs": [],
      "properties": {
        "ligatures": "neutral, emoticon25",
        "name": "neutral",
        "order": 47,
        "id": 248,
        "prevSize": 32,
        "code": 59895
      },
      "setIdx": 0,
      "setId": 1,
      "iconIdx": 247
    },
    {
      "icon": {
        "paths": [
          "M512 0c-282.77 0-512 229.23-512 512s229.226 512 512 512c282.77 0 512-229.23 512-512s-229.23-512-512-512zM640 768h-256v-64h256v64zM704 256c35.346 0 64 28.654 64 64s-28.654 64-64 64-64-28.654-64-64c0-35.346 28.654-64 64-64zM320 256c35.346 0 64 28.654 64 64s-28.654 64-64 64-64-28.654-64-64c0-35.346 28.654-64 64-64z"
        ],
        "tags": [
          "neutral",
          "emoticon",
          "smiley",
          "face"
        ],
        "defaultCode": 59896,
        "grid": 16,
        "attrs": []
      },
      "attrs": [],
      "properties": {
        "ligatures": "neutral2, emoticon26",
        "name": "neutral2",
        "order": 48,
        "id": 249,
        "prevSize": 32,
        "code": 59896
      },
      "setIdx": 0,
      "setId": 1,
      "iconIdx": 248
    },
    {
      "icon": {
        "paths": [
          "M512 1024c282.77 0 512-229.23 512-512s-229.23-512-512-512-512 229.23-512 512 229.23 512 512 512zM512 96c229.75 0 416 186.25 416 416s-186.25 416-416 416-416-186.25-416-416 186.25-416 416-416zM256 320c0-35.346 28.654-64 64-64s64 28.654 64 64-28.654 64-64 64-64-28.654-64-64zM640 320c0-35.346 28.654-64 64-64s64 28.654 64 64-28.654 64-64 64-64-28.654-64-64z",
          "M675.882 540.118c-37.49-37.49-98.276-37.49-135.766 0s-37.49 98.276 0 135.766c1.204 1.204 2.434 2.368 3.684 3.492 86.528 78.512 288.2-1.842 288.2-103.376-62 40-110.45 9.786-156.118-35.882z",
          "M348.118 540.118c37.49-37.49 98.276-37.49 135.766 0s37.49 98.276 0 135.766c-1.204 1.204-2.434 2.368-3.684 3.492-86.528 78.512-288.2-1.842-288.2-103.376 62 40 110.45 9.786 156.118-35.882z"
        ],
        "tags": [
          "hipster",
          "emoticon",
          "smiley",
          "mustache",
          "face"
        ],
        "defaultCode": 59897,
        "grid": 16,
        "attrs": []
      },
      "attrs": [],
      "properties": {
        "ligatures": "hipster, emoticon27",
        "name": "hipster",
        "order": 49,
        "id": 250,
        "prevSize": 32,
        "code": 59897
      },
      "setIdx": 0,
      "setId": 1,
      "iconIdx": 249
    },
    {
      "icon": {
        "paths": [
          "M512 0c-282.77 0-512 229.23-512 512s229.23 512 512 512 512-229.23 512-512-229.23-512-512-512zM704 256c35.346 0 64 28.654 64 64s-28.654 64-64 64-64-28.654-64-64 28.654-64 64-64zM320 256c35.346 0 64 28.654 64 64s-28.654 64-64 64-64-28.654-64-64 28.654-64 64-64zM543.8 679.376c-1.25-1.124-2.48-2.29-3.684-3.492-18.74-18.74-28.112-43.3-28.118-67.864-0.004 24.562-9.376 49.124-28.118 67.864-1.204 1.204-2.434 2.368-3.684 3.492-86.524 78.512-288.196-1.842-288.196-103.376 62 40 110.45 9.786 156.118-35.882 37.49-37.49 98.276-37.49 135.766 0 18.74 18.74 28.112 43.3 28.118 67.864 0.004-24.562 9.376-49.124 28.118-67.864 37.49-37.49 98.276-37.49 135.766 0 45.664 45.668 94.114 75.882 156.114 35.882 0 101.534-201.672 181.888-288.2 103.376z"
        ],
        "tags": [
          "hipster",
          "emoticon",
          "smiley",
          "mustache",
          "face"
        ],
        "defaultCode": 59898,
        "grid": 16,
        "attrs": []
      },
      "attrs": [],
      "properties": {
        "ligatures": "hipster2, emoticon28",
        "name": "hipster2",
        "order": 50,
        "id": 251,
        "prevSize": 32,
        "code": 59898
      },
      "setIdx": 0,
      "setId": 1,
      "iconIdx": 250
    },
    {
      "icon": {
        "paths": [
          "M512 1024c282.77 0 512-229.23 512-512s-229.23-512-512-512-512 229.23-512 512 229.23 512 512 512zM512 96c229.75 0 416 186.25 416 416s-186.25 416-416 416-416-186.25-416-416 186.25-416 416-416zM745.74 601.62l22.488 76.776-437.008 128.002-22.488-76.776zM256 320c0-35.346 28.654-64 64-64s64 28.654 64 64c0 35.346-28.654 64-64 64s-64-28.654-64-64zM640 320c0-35.346 28.654-64 64-64s64 28.654 64 64c0 35.346-28.654 64-64 64s-64-28.654-64-64z"
        ],
        "tags": [
          "wondering",
          "emoticon",
          "smiley",
          "face",
          "question"
        ],
        "defaultCode": 59899,
        "grid": 16,
        "attrs": []
      },
      "attrs": [],
      "properties": {
        "ligatures": "wondering, emoticon29",
        "name": "wondering",
        "order": 51,
        "id": 252,
        "prevSize": 32,
        "code": 59899
      },
      "setIdx": 0,
      "setId": 1,
      "iconIdx": 251
    },
    {
      "icon": {
        "paths": [
          "M512 0c-282.77 0-512 229.23-512 512s229.23 512 512 512 512-229.23 512-512-229.23-512-512-512zM704 256c35.346 0 64 28.654 64 64s-28.654 64-64 64-64-28.654-64-64 28.654-64 64-64zM256 320c0-35.346 28.654-64 64-64s64 28.654 64 64-28.654 64-64 64-64-28.654-64-64zM331.244 806.386l-22.488-76.774 437-128 22.488 76.774-437 128z"
        ],
        "tags": [
          "wondering",
          "emoticon",
          "smiley",
          "face",
          "question"
        ],
        "defaultCode": 59900,
        "grid": 16,
        "attrs": []
      },
      "attrs": [],
      "properties": {
        "ligatures": "wondering2, emoticon30",
        "name": "wondering2",
        "order": 74,
        "id": 253,
        "prevSize": 32,
        "code": 59900
      },
      "setIdx": 0,
      "setId": 1,
      "iconIdx": 252
    },
    {
      "icon": {
        "paths": [
          "M512 1024c282.77 0 512-229.23 512-512s-229.23-512-512-512-512 229.23-512 512 229.23 512 512 512zM512 96c229.75 0 416 186.25 416 416s-186.25 416-416 416-416-186.25-416-416 186.25-416 416-416z",
          "M640 672c0 88.366-57.308 160-128.002 160s-128.002-71.634-128.002-160c0-88.366 57.308-160 128.002-160s128.002 71.634 128.002 160z",
          "M416 340c-8.19 0-16.378-3.124-22.626-9.374-19.334-19.332-63.412-19.332-82.746 0-12.496 12.498-32.758 12.498-45.254 0-12.498-12.496-12.498-32.758 0-45.254 44.528-44.53 128.726-44.53 173.254 0 12.498 12.496 12.498 32.758 0 45.254-6.248 6.25-14.438 9.374-22.628 9.374z",
          "M736 340c-8.19 0-16.378-3.124-22.626-9.374-19.332-19.332-63.414-19.332-82.746 0-12.496 12.498-32.758 12.498-45.254 0-12.498-12.496-12.498-32.758 0-45.254 44.528-44.53 128.726-44.53 173.254 0 12.498 12.496 12.498 32.758 0 45.254-6.248 6.25-14.438 9.374-22.628 9.374z"
        ],
        "tags": [
          "sleepy",
          "emoticon",
          "smiley",
          "face"
        ],
        "defaultCode": 59901,
        "grid": 16,
        "attrs": []
      },
      "attrs": [],
      "properties": {
        "ligatures": "sleepy, emoticon31",
        "name": "sleepy",
        "order": 75,
        "id": 254,
        "prevSize": 32,
        "code": 59901
      },
      "setIdx": 0,
      "setId": 1,
      "iconIdx": 253
    },
    {
      "icon": {
        "paths": [
          "M512 0c-282.77 0-512 229.23-512 512s229.23 512 512 512 512-229.23 512-512-229.23-512-512-512zM310.628 330.626c-12.496 12.498-32.758 12.498-45.254 0-12.498-12.496-12.498-32.758 0-45.254 44.528-44.53 128.726-44.53 173.254 0 12.498 12.496 12.498 32.758 0 45.254-6.248 6.25-14.438 9.374-22.628 9.374s-16.378-3.124-22.626-9.374c-19.334-19.332-63.412-19.332-82.746 0zM511.998 832c-70.694 0-128.002-71.634-128.002-160s57.308-160 128.002-160 128.002 71.634 128.002 160-57.308 160-128.002 160zM758.628 330.626c-6.248 6.25-14.438 9.374-22.628 9.374s-16.378-3.124-22.626-9.374c-19.332-19.332-63.414-19.332-82.746 0-12.496 12.498-32.758 12.498-45.254 0-12.498-12.496-12.498-32.758 0-45.254 44.528-44.53 128.726-44.53 173.254 0 12.498 12.498 12.498 32.758 0 45.254z"
        ],
        "tags": [
          "sleepy",
          "emoticon",
          "smiley",
          "face"
        ],
        "defaultCode": 59902,
        "grid": 16,
        "attrs": []
      },
      "attrs": [],
      "properties": {
        "ligatures": "sleepy2, emoticon32",
        "name": "sleepy2",
        "order": 76,
        "id": 255,
        "prevSize": 32,
        "code": 59902
      },
      "setIdx": 0,
      "setId": 1,
      "iconIdx": 254
    },
    {
      "icon": {
        "paths": [
          "M366.312 283.378c-34.742-17.37-69.102-26.060-70.548-26.422-17.146-4.288-34.518 6.138-38.806 23.284-4.284 17.144 6.14 34.518 23.282 38.804 17.626 4.45 38.522 12.12 56.936 21.35-10.648 11.43-17.174 26.752-17.174 43.606 0 35.346 28.654 64 64 64s64-28.654 64-64c0-1.17-0.036-2.33-0.098-3.484-2.032-47.454-45.212-78.946-81.592-97.138z",
          "M512 0c-282.77 0-512 229.23-512 512s229.23 512 512 512 512-229.23 512-512-229.23-512-512-512zM236.498 823.664c10.706 5.324 22.756 8.336 35.502 8.336h480c12.746 0 24.796-3.012 35.502-8.338-73.378 64.914-169.828 104.338-275.502 104.338-105.672 0-202.124-39.424-275.502-104.336zM256 752v-96c0-8.674 7.328-16 16-16h112v128h-112c-8.672 0-16-7.326-16-16zM448 768v-128h128v128h-128zM640 768v-128h112c8.674 0 16 7.326 16 16v96c0 8.674-7.326 16-16 16h-112zM823.662 787.502c5.326-10.706 8.338-22.756 8.338-35.502v-96c0-44.112-35.888-80-80-80h-480c-44.112 0-80 35.888-80 80v96c0 12.746 3.012 24.796 8.336 35.502-64.912-73.378-104.336-169.828-104.336-275.502 0-229.75 186.25-416 416-416s416 186.25 416 416c0 105.674-39.424 202.124-104.338 275.502z",
          "M728.236 256.956c-1.448 0.362-35.806 9.052-70.548 26.422-36.378 18.192-79.558 49.684-81.592 97.138-0.060 1.154-0.098 2.314-0.098 3.484 0 35.346 28.654 64 64 64s64-28.654 64-64c0-16.854-6.526-32.176-17.174-43.606 18.414-9.23 39.31-16.9 56.936-21.35 17.142-4.286 27.566-21.66 23.284-38.804-4.29-17.146-21.662-27.572-38.808-23.284z"
        ],
        "tags": [
          "frustrated",
          "emoticon",
          "smiley",
          "face",
          "angry"
        ],
        "defaultCode": 59903,
        "grid": 16,
        "attrs": []
      },
      "attrs": [],
      "properties": {
        "ligatures": "frustrated, emoticon33",
        "name": "frustrated",
        "order": 67,
        "id": 256,
        "prevSize": 32,
        "code": 59903
      },
      "setIdx": 0,
      "setId": 1,
      "iconIdx": 255
    },
    {
      "icon": {
        "paths": [
          "M256 656v96c0 8.674 7.328 16 16 16h112v-128h-112c-8.672 0-16 7.326-16 16z",
          "M448 640h128v128h-128v-128z",
          "M752 640h-112v128h112c8.674 0 16-7.326 16-16v-96c0-8.674-7.326-16-16-16z",
          "M512 0c-282.77 0-512 229.23-512 512s229.23 512 512 512 512-229.23 512-512-229.23-512-512-512zM576.096 380.516c2.034-47.454 45.212-78.946 81.592-97.138 34.742-17.37 69.102-26.060 70.548-26.422 17.146-4.288 34.518 6.138 38.806 23.284 4.284 17.144-6.14 34.518-23.284 38.804-17.624 4.45-38.522 12.12-56.936 21.35 10.648 11.43 17.174 26.752 17.174 43.606 0 35.346-28.654 64-64 64s-64-28.654-64-64c0.002-1.17 0.040-2.33 0.1-3.484zM256.958 280.24c4.288-17.146 21.66-27.572 38.806-23.284 1.446 0.362 35.806 9.052 70.548 26.422 36.38 18.192 79.56 49.684 81.592 97.138 0.062 1.154 0.098 2.314 0.098 3.484 0 35.346-28.654 64-64 64s-64-28.654-64-64c0-16.854 6.526-32.176 17.174-43.606-18.414-9.23-39.31-16.9-56.936-21.35-17.142-4.286-27.566-21.66-23.282-38.804zM832 752c0 44.112-35.888 80-80 80h-480c-44.112 0-80-35.888-80-80v-96c0-44.112 35.888-80 80-80h480c44.112 0 80 35.888 80 80v96z"
        ],
        "tags": [
          "frustrated",
          "emoticon",
          "smiley",
          "face",
          "angry"
        ],
        "defaultCode": 59904,
        "grid": 16,
        "attrs": []
      },
      "attrs": [],
      "properties": {
        "ligatures": "frustrated2, emoticon34",
        "name": "frustrated2",
        "order": 68,
        "id": 257,
        "prevSize": 32,
        "code": 59904
      },
      "setIdx": 0,
      "setId": 1,
      "iconIdx": 256
    },
    {
      "icon": {
        "paths": [
          "M512 1024c282.77 0 512-229.23 512-512s-229.23-512-512-512-512 229.23-512 512 229.23 512 512 512zM512 96c229.75 0 416 186.25 416 416s-186.25 416-416 416-416-186.25-416-416 186.25-416 416-416z",
          "M800 384h-128c-17.674 0-32-14.328-32-32s14.326-32 32-32h128c17.674 0 32 14.328 32 32s-14.326 32-32 32z",
          "M352 384h-128c-17.672 0-32-14.328-32-32s14.328-32 32-32h128c17.672 0 32 14.328 32 32s-14.328 32-32 32z",
          "M608 856c-8.19 0-16.378-3.124-22.626-9.374-4.582-4.582-29.42-14.626-73.374-14.626s-68.79 10.044-73.374 14.626c-12.496 12.496-32.758 12.496-45.254 0-12.498-12.496-12.498-32.758 0-45.254 30.122-30.12 92.994-33.372 118.628-33.372 25.632 0 88.506 3.252 118.626 33.374 12.498 12.496 12.498 32.758 0 45.254-6.248 6.248-14.436 9.372-22.626 9.372z",
          "M736 576c-17.674 0-32-14.326-32-32v-64c0-17.672 14.326-32 32-32s32 14.328 32 32v64c0 17.674-14.326 32-32 32z",
          "M736 768c-17.674 0-32-14.326-32-32v-64c0-17.674 14.326-32 32-32s32 14.326 32 32v64c0 17.674-14.326 32-32 32z",
          "M288 576c-17.672 0-32-14.326-32-32v-64c0-17.672 14.328-32 32-32s32 14.328 32 32v64c0 17.674-14.328 32-32 32z",
          "M288 768c-17.672 0-32-14.326-32-32v-64c0-17.674 14.328-32 32-32s32 14.326 32 32v64c0 17.674-14.328 32-32 32z"
        ],
        "tags": [
          "crying",
          "emoticon",
          "smiley",
          "face"
        ],
        "defaultCode": 59905,
        "grid": 16,
        "attrs": []
      },
      "attrs": [],
      "properties": {
        "ligatures": "crying, emoticon35",
        "name": "crying",
        "order": 69,
        "id": 258,
        "prevSize": 32,
        "code": 59905
      },
      "setIdx": 0,
      "setId": 1,
      "iconIdx": 257
    },
    {
      "icon": {
        "paths": [
          "M512 0c-282.77 0-512 229.23-512 512s229.23 512 512 512 512-229.23 512-512-229.23-512-512-512zM320 736c0 17.674-14.328 32-32 32s-32-14.326-32-32v-64c0-17.674 14.328-32 32-32s32 14.326 32 32v64zM320 544c0 17.674-14.328 32-32 32s-32-14.326-32-32v-64c0-17.672 14.328-32 32-32s32 14.328 32 32v64zM352 384h-128c-17.672 0-32-14.328-32-32s14.328-32 32-32h128c17.672 0 32 14.328 32 32s-14.328 32-32 32zM630.626 846.626c-6.248 6.25-14.436 9.374-22.626 9.374s-16.378-3.124-22.626-9.374c-4.582-4.582-29.42-14.626-73.374-14.626s-68.79 10.044-73.374 14.626c-12.496 12.496-32.758 12.496-45.254 0-12.498-12.496-12.498-32.758 0-45.254 30.122-30.12 92.994-33.372 118.628-33.372 25.632 0 88.506 3.252 118.626 33.374 12.498 12.496 12.498 32.756 0 45.252zM768 736c0 17.674-14.326 32-32 32s-32-14.326-32-32v-64c0-17.674 14.326-32 32-32s32 14.326 32 32v64zM768 544c0 17.674-14.326 32-32 32s-32-14.326-32-32v-64c0-17.672 14.326-32 32-32s32 14.328 32 32v64zM800 384h-128c-17.674 0-32-14.328-32-32s14.326-32 32-32h128c17.674 0 32 14.328 32 32s-14.326 32-32 32z"
        ],
        "tags": [
          "crying",
          "emoticon",
          "smiley",
          "face"
        ],
        "defaultCode": 59906,
        "grid": 16,
        "attrs": []
      },
      "attrs": [],
      "properties": {
        "ligatures": "crying2, emoticon36",
        "name": "crying2",
        "order": 70,
        "id": 259,
        "prevSize": 32,
        "code": 59906
      },
      "setIdx": 0,
      "setId": 1,
      "iconIdx": 258
    }
  ],
  "height": 1024,
  "metadata": {
    "name": "smilies"
  },
  "preferences": {
    "showGlyphs": true,
    "showQuickUse": true,
    "showQuickUse2": true,
    "showSVGs": true,
    "fontPref": {
      "prefix": "icom-",
      "metadata": {
        "fontFamily": "smilies",
        "majorVersion": 1,
        "minorVersion": 0
      },
      "metrics": {
        "emSize": 1024,
        "baseline": 6.25,
        "whitespace": 50
      },
      "embed": false
    },
    "imagePref": {
      "prefix": "icon-",
      "png": true,
      "useClassSelector": true,
      "color": 0,
      "bgColor": 16777215,
      "classSelector": ".icon"
    },
    "historySize": 100,
    "showCodes": true,
    "gridSize": 16
  }
}